<Resources>
  <string id="%1%" value="呼び径"/>
  <string id="%2%" value="最小クリアランス"/>
  <string id="%3%" value="標準クリアランス"/>
  <string id="%4%" value="最大クリアランス"/>
  <string id="%5%" value="頭部の直径"/>
  <string id="%6%" value="ざぐり深さ"/>
  <string id="%7%" value="皿面取り角度"/>
  <string id="%8%" value="JIS ドリル穴"/>
  <string id="%9%" value="JIS 皿小ねじ"/>
  <string id="%10%" value="JIS 丸皿小ねじ"/>
  <string id="%11%" value="JIS 六角小ねじ"/>
  <string id="%12%" value="JIS 六角ボルト"/>
  <string id="%13%" value="JIS 六角小ねじ"/>
  <string id="%14%" value="JIS 六角穴付き小ねじ"/>
</Resources>